lambdata/__init__.py
lambdata-0.0.2.dist-info/LICENSE
lambdata-0.0.2.dist-info/METADATA
lambdata-0.0.2.dist-info/WHEEL
lambdata-0.0.2.dist-info/top_level.txt
lambdata-0.0.2.dist-info/RECORD
