Metadata-Version: 2.1
Name: lambdata
Version: 0.0.2
Summary: A collection of Data Science helper functions
Home-page: https://lambdaschool.com/courses/data-science/
Author: soycode
License: UNKNOWN
Platform: UNKNOWN
Classifier: Programming Language :: Python :: 3
Classifier: License :: OSI Approved :: MIT License
Classifier: Operating System :: OS Independent
Requires-Python: >=3.5
Requires-Dist: numpy
Requires-Dist: pandas
